micro_logger.py
micro_logger_unittest.py
micro_logger-0.1.4.dist-info/LICENSE.txt
micro_logger-0.1.4.dist-info/METADATA
micro_logger-0.1.4.dist-info/WHEEL
micro_logger-0.1.4.dist-info/top_level.txt
micro_logger-0.1.4.dist-info/RECORD
