Metadata-Version: 2.1
Name: micro-logger
Version: 0.1.4
Summary: A JSON logger made for microservices
Home-page: https://github.com/gaf3/python-micro-logger
Author: Gaffer Fitch
Author-email: micro-logger@gaf3.com
Classifier: Programming Language :: Python :: 3
Classifier: License :: OSI Approved :: MIT License
License-File: LICENSE.txt
Requires-Dist: python-json-logger ==2.0.2
